termcolor/__init__.py
termcolor/__main__.py
termcolor_whl-1.1.3.dist-info/LICENSE
termcolor_whl-1.1.3.dist-info/METADATA
termcolor_whl-1.1.3.dist-info/WHEEL
termcolor_whl-1.1.3.dist-info/entry_points.txt
termcolor_whl-1.1.3.dist-info/RECORD
