Metadata-Version: 2.1
Name: termcolor-whl
Version: 1.1.3
Summary: ANSI Color formatting for output in terminal, fork of termcolor, maintained as of 2023 by Matthew Martin
Home-page: https://github.com/matthewdeanmartin/termcolor
License: MIT
Keywords: terminals,ansi
Author: Konstantin Lepa
Author-email: konstantin.lepa@gmail.com
Requires-Python: >=2.6
Classifier: Development Status :: 5 - Production/Stable
Classifier: Environment :: Console
Classifier: Intended Audience :: Developers
Classifier: License :: OSI Approved :: MIT License
Classifier: Operating System :: OS Independent
Classifier: Programming Language :: Python
Classifier: Programming Language :: Python :: 2
Classifier: Programming Language :: Python :: 2.7
Classifier: Programming Language :: Python :: 3
Classifier: Programming Language :: Python :: 3.4
Classifier: Programming Language :: Python :: 3.5
Classifier: Programming Language :: Python :: 3.6
Classifier: Programming Language :: Python :: 3.7
Classifier: Programming Language :: Python :: 3.8
Classifier: Programming Language :: Python :: 3.9
Classifier: Programming Language :: Python :: 3.10
Classifier: Programming Language :: Python :: 3.11
Classifier: Programming Language :: Python :: 2.6
Classifier: Topic :: Terminals
Project-URL: Bug Tracker, https://github.com/matthewdeanmartin/termcolor/issues
Project-URL: Change Log, https://github.com/matthewdeanmartin/termcolor/blob/main/docs/CHANGES.MD
Project-URL: Documentation, https://github.com/matthewdeanmartin/termcolor
Project-URL: Repository, https://github.com/matthewdeanmartin/termcolor
